HISTORY.md
LICENSE
MANIFEST.in
README.MD
README.md
requirements.txt
setup.cfg
setup.py
demo/demo.py
docs/api.md
tests/test.txt
xlrw/__init__.py
xlrw/__version__.py
xlrw/xlrw.py
xlrw.egg-info/PKG-INFO
xlrw.egg-info/SOURCES.txt
xlrw.egg-info/dependency_links.txt
xlrw.egg-info/requires.txt
xlrw.egg-info/top_level.txt