Metadata-Version: 1.2
Name: xlrw
Version: 0.0.2
Summary: xlrw is a Python library to read/write Excel files.
Home-page: https://github.com/liukecode/xlrw.git
Author: Liuke
Author-email: UNKNOWN
License: UNKNOWN
Keywords: python,xlrw
Platform: any
Classifier: Programming Language :: Python :: 3
Classifier: License :: OSI Approved :: GNU General Public License (GPL)
Classifier: Operating System :: OS Independent
Requires-Python: >=3
